nametract/__init__.py
nametract/extractor.py
nametract/tokenizer.py
nametract-1.1.3.dist-info/LICENSE
nametract-1.1.3.dist-info/WHEEL
nametract-1.1.3.dist-info/METADATA
nametract-1.1.3.dist-info/RECORD
