Metadata-Version: 2.1
Name: nametract
Version: 1.1.3
Summary: Simple and stupid name extraction
Home-page: https://github.com/keddad/nametract
License: MIT
Keywords: extractor,names
Author: keddad
Author-email: keddad@yandex.ru
Requires-Python: >=3.6,<4.0
Classifier: Development Status :: 4 - Beta
Classifier: License :: OSI Approved :: MIT License
Classifier: Programming Language :: Python :: 3
Classifier: Programming Language :: Python :: 3 :: Only
Classifier: Programming Language :: Python :: 3.6
Classifier: Programming Language :: Python :: 3.7
Classifier: Programming Language :: Python :: 3.8
Classifier: Programming Language :: Python :: 3.9
Project-URL: Repository, https://github.com/keddad/nametract
